[
  {
    "type": "screen_backgroundColor",
    "message0": "%{BKY_SET_BACKGROUND_COLOR} %1",
    "args0": [
      {
        "type": "field_dropdown",
        "name": "COLOR",
        "options": [
          [ "%{BKY_COLOR_BLACK}", "BLACK" ],
          [ "%{BKY_COLOR_RED}", "RED" ],
          [ "%{BKY_COLOR_ORANGE}", "ORANGE" ],
          [ "%{BKY_COLOR_BROWN}", "BROWN" ],
          [ "%{BKY_COLOR_YELLOW}", "YELLOW" ],
          [ "%{BKY_COLOR_BLUE}", "BLUE" ],
          [ "%{BKY_COLOR_TURQUOISE}", "TURQUOISE" ],
          [ "%{BKY_COLOR_GREEN}", "GREEN" ],
          [ "%{BKY_COLOR_PURPLE}", "PURPLE" ],
          [ "%{BKY_COLOR_WHITE}", "WHITE" ]
        ]
      }
    ],
    "previousStatement": null,
    "nextStatement":  null
  },

  {
    "type": "screen_setColorRGB",
    "message0": "%{BKY_SET_BACKGROUND_COLOR_RGB}",
    "args0": [
      {
        "type": "field_label"
      }
    ],
    "message1": "%{BKY_RGB_RED} %1 %{BKY_RGB_GREEN} %2 %{BKY_RGB_BLUE} %3",
    "args1": [
      {
        "type": "field_number",
        "name": "RGB_RED",
        "value": "0",
        "min": "0",
        "max": "255",
        "int": true
      },
      {
        "type": "field_number",
        "name": "RGB_GREEN",
        "value": "0",
        "min": "0",
        "max": "255",
        "int": true
      },
      {
        "type": "field_number",
        "name": "RGB_BLUE",
        "value": "0",
        "min": "0",
        "max": "255",
        "int": true
      }
    ],
    "previousStatement": null,
    "nextStatement": null
  },

  {
    "type": "screen_backgroundBrightness",
    "message0": "%{BKY_SET_BACKGROUND_BRIGHTNESS} %1",
    "args0": [
      {
        "type": "input_value",
        "name": "BRIGHTNESS",
        "check": "Number",
        "align": "RIGHT"
      }
    ],
    "previousStatement": null,
    "nextStatement": null
  }
]